drb/addons/metadata/file/__init__.py
drb/addons/metadata/file/_version.py
drb/addons/metadata/file/cortex.yml
drb_metadata_file-1.1.0.dist-info/METADATA
drb_metadata_file-1.1.0.dist-info/WHEEL
drb_metadata_file-1.1.0.dist-info/entry_points.txt
drb_metadata_file-1.1.0.dist-info/top_level.txt
drb_metadata_file-1.1.0.dist-info/RECORD
