Metadata-Version: 2.1
Name: drb-metadata-file
Version: 1.1.0
Summary: File Metadata
Author: GAEL Systems
Author-email: drb-python@gael.fr
License: LGPLv3
Project-URL: Source, https://gitlab.com/drb-python/add-ons/metadata/add-ons/file
Classifier: Programming Language :: Python :: 3.8
Classifier: License :: OSI Approved :: GNU Lesser General Public License v3 (LGPLv3)
Requires-Python: >=3.8
Requires-Dist: drb-metadata ~=1.3.0
